{
	"name": "supplier",
	"package": "purchasing",
	"versionnable": false,
	"promotionControlled": false,
	"ui": {
		"defaultThumbnail": "images/supplierLogo.png",
		"gridColumns": [
			{
				"id": "uigc_111b1d5ce53cc32b795a2316dbd3226a",
				"type": "string",
				"property": "supplier.name",
				"order": 1
			},
			{
				"id": "uigc_9757ba20-2da7-11ec-814d-c78900074d18",
				"name": "col_1",
				"type": "string",
				"property": "supplier.location",
				"order": 2
			}
		],
		"form": {
			"definition": {
				"A": [
					{
						"type": "item",
						"id": 2,
						"property": "name",
						"readOnly": false,
						"size": "2",
						"offset": "0",
						"propertyType": "string"
					},
					{
						"type": "item",
						"id": "it_387a4590-0a9f-44aa-9397-aa664d17b202",
						"size": "2",
						"property": "location",
						"propertyType": "string",
						"readOnly": false,
						"offset": "0"
					}
				]
			},
			"ng": {},
			"labelCase": "capitalize"
		},
		"tabs": []
	},
	"lifecycle": {
		"states": [
			{
				"name": "state 0",
				"label": "state 0",
				"start": true,
				"lockable": true,
				"id": "state_896e0e7bf79c902831849e500863d019"
			}
		],
		"transitions": [],
		"roles": []
	},
	"category": 7,
	"configuration": false,
	"classification": [],
	"properties": [
		{
			"id": "prop_376efbe4c47504348ac9ad0dc4d48e9f",
			"name": "_id",
			"type": "string",
			"unique": true,
			"mandatory": false,
			"generated": "api",
			"core": true,
			"translations": {
				"default": "_id",
				"fr": "ID"
			}
		},
		{
			"id": "prop_5bd2f982d01f1e37efac0221eba7a7f8",
			"name": "_ref",
			"type": "string",
			"unique": true,
			"mandatory": false,
			"generated": false,
			"core": true,
			"translations": {
				"default": "_ref",
				"fr": "Ref"
			}
		},
		{
			"id": "prop_0c7b22186a989959710a2ed22eaa969c",
			"name": "_state",
			"type": "state",
			"unique": false,
			"mandatory": false,
			"generated": "api",
			"core": true,
			"translations": {
				"default": "_state",
				"fr": "Statut"
			}
		},
		{
			"id": "prop_4f259f66593f3371bfe2b64a8eaf03e6",
			"name": "_createdOn",
			"type": "date",
			"unique": false,
			"mandatory": false,
			"generated": "api",
			"core": true,
			"translations": {
				"default": "_createdOn",
				"fr": "Créé le"
			}
		},
		{
			"id": "prop_ffa766f0508a84bada08fc98e78c11fe",
			"name": "_modifiedOn",
			"type": "date",
			"unique": false,
			"mandatory": false,
			"generated": "api",
			"core": true,
			"translations": {
				"default": "_modifiedOn",
				"fr": "Modifié le"
			}
		},
		{
			"id": "prop_5fae58d859953f212333d3e555acc3d2",
			"name": "_lockable",
			"type": "boolean",
			"unique": false,
			"mandatory": false,
			"generated": "api",
			"core": true,
			"translations": {
				"default": "_lockable"
			}
		},
		{
			"id": "prop_30aeb5cb6792a81167833e4c732025a5",
			"name": "_lockedByName",
			"type": "string",
			"unique": false,
			"mandatory": false,
			"generated": "api",
			"core": true,
			"translations": {
				"default": "_lockedByName"
			}
		},
		{
			"id": "prop_19cff3574a55b04871cc3b9282d26d86",
			"name": "_lockState",
			"type": "boolean",
			"unique": false,
			"mandatory": false,
			"generated": false,
			"core": true,
			"translations": {
				"default": "Lockstate"
			}
		},
		{
			"name": "_thumbnail",
			"type": "node",
			"unique": false,
			"mandatory": false,
			"generated": false,
			"core": true,
			"relationship": "nt_5d79e3adnkcd25615637df85e122bcac",
			"id": "prop_b7bf0065-c426-11e9-9ce5-63afa77a96d0",
			"translations": {
				"default": "_thumbnail",
				"fr": "Vignette"
			}
		},
		{
			"name": "_releasedOn",
			"type": "date",
			"unique": false,
			"mandatory": false,
			"generated": "api",
			"core": true,
			"id": "prop_b7bf0066-c426-11e9-9ce5-63afa77a96d0",
			"translations": {
				"default": "_releasedOn",
				"fr": "Validé le"
			}
		},
		{
			"name": "_version",
			"type": "string",
			"unique": false,
			"mandatory": false,
			"generated": "api",
			"core": true,
			"id": "prop_b7bf0067-c426-11e9-9ce5-63afa77a96d0",
			"translations": {
				"default": "_version",
				"fr": "Révision"
			}
		},
		{
			"name": "_versionedOn",
			"type": "date",
			"unique": false,
			"mandatory": false,
			"generated": "api",
			"core": true,
			"id": "prop_b7bf0068-c426-11e9-9ce5-63afa77a96d0",
			"translations": {
				"default": "_versionedOn",
				"fr": "Révisé le"
			}
		},
		{
			"name": "_history",
			"type": "json",
			"unique": false,
			"mandatory": false,
			"generated": "api",
			"core": true,
			"id": "prop_b7bf006a-c426-11e9-9ce5-63afa77a96d0",
			"translations": {
				"default": "_history",
				"fr": "Historique"
			}
		},
		{
			"name": "_promotions",
			"type": "json",
			"unique": false,
			"mandatory": false,
			"generated": "api",
			"core": true,
			"id": "prop_b7bf006b-c426-11e9-9ce5-63afa77a96d0",
			"translations": {
				"default": "_promotions",
				"fr": "Promotions"
			}
		},
		{
			"name": "_serialized",
			"type": "multiselect",
			"unique": false,
			"mandatory": false,
			"generated": false,
			"core": true,
			"id": "prop_b7bf006c-c426-11e9-9ce5-63afa77a96d0",
			"translations": {
				"default": "_serialized"
			}
		},
		{
			"name": "_createdBy",
			"type": "text",
			"unique": false,
			"mandatory": false,
			"generated": "api",
			"core": true,
			"id": "prop_b7bf006d-c426-11e9-9ce5-63afa77a96d0",
			"translations": {
				"default": "_createdBy"
			}
		},
		{
			"name": "_lockedBy",
			"type": "string",
			"unique": false,
			"mandatory": false,
			"generated": "api",
			"core": true,
			"id": "prop_b7bf006e-c426-11e9-9ce5-63afa77a96d0",
			"translations": {
				"default": "_lockedBy"
			}
		},
		{
			"name": "_lockedOn",
			"type": "date",
			"unique": false,
			"mandatory": false,
			"generated": "api",
			"core": true,
			"id": "prop_b7bf006f-c426-11e9-9ce5-63afa77a96d0",
			"translations": {
				"default": "_lockedOn"
			}
		},
		{
			"id": "prop_ae0212e0-1024-11ea-b010-8f2637fd5f12",
			"name": "_createdByName",
			"type": "text",
			"unique": false,
			"mandatory": false,
			"generated": "api",
			"core": true,
			"translations": {
				"default": "Created By Name",
				"fr": "Créé par"
			}
		},
		{
			"name": "_releasedUntil",
			"type": "date",
			"unique": false,
			"mandatory": false,
			"generated": "api",
			"core": false,
			"id": "prop_938d35b0-6556-11eb-94db-07bad80f0c9e",
			"translations": {
				"default": "_releasedUntil",
				"fr": "Valide jusqu'à"
			}
		},
		{
			"id": "prop_f44109337bc33f84d1b237958af02ad1",
			"name": "name",
			"type": "string",
			"unique": false,
			"mandatory": false,
			"generated": false,
			"core": false,
			"translations": {
				"default": "Name",
				"fr": "Nom"
			}
		},
		{
			"id": "prop_953aa680-2da7-11ec-814d-c78900074d18",
			"name": "location",
			"type": "string",
			"unique": false,
			"mandatory": false,
			"generated": false,
			"infoData": false,
			"core": false,
			"translations": {
				"default": "Location",
				"fr": "Location"
			}
		}
	],
	"maidenName": {
		"elements": [
			"name"
		],
		"separator": "-"
	},
	"actions": [],
	"elementType": "node",
	"id": "nt_9a36454795be674e7f03bb02b4b60164",
	"hiddenLifecycle": true,
	"methods": [],
	"translations": {
		"default": "Supplier",
		"en": "Supplier",
		"fr": "Fournisseur",
		"el": "Προμηθευτής"
	}
}